README.md
setup.py
elements/__init__.py
elements/attrdict.py
elements/cache.py
elements/checkpoint.py
elements/config.py
elements/metrics.py
elements/nest.py
elements/plot.py
elements/tools.py
elementspy.egg-info/PKG-INFO
elementspy.egg-info/SOURCES.txt
elementspy.egg-info/dependency_links.txt
elementspy.egg-info/top_level.txt