Metadata-Version: 1.1
Name: elementspy
Version: 0.1.0
Summary: Building blocks for productive research.
Home-page: http://github.com/danijar/elements
Author: UNKNOWN
Author-email: UNKNOWN
License: UNKNOWN
Platform: UNKNOWN
Classifier: Programming Language :: Python :: 3
Classifier: Topic :: Scientific/Engineering :: Visualization
Classifier: License :: OSI Approved :: Apache Software License
